esek/Calculator/__init__.py
esek/Calculator/Proportions/multiple_proportions.py
esek/Calculator/Proportions/one_sample_proportion.py
esek/Calculator/Proportions/two_dependent_proportions.py
esek/Calculator/Proportions/two_independent_proportions.py
esek/Calculator/one_sample_mean/__init__.py
esek/Calculator/one_sample_mean/one_sample_aparametric.py
esek/Calculator/one_sample_mean/one_sample_cles.py
esek/Calculator/one_sample_mean/one_sample_t.py
esek/Calculator/one_sample_mean/one_sample_z.py
esek/Calculator/two_independent_mean/__init__.py
esek/Calculator/two_independent_mean/two_independent_aparametric.py
esek/Calculator/two_independent_mean/two_independent_control_group.py
esek/Calculator/two_independent_mean/two_independent_robust.py
esek/Calculator/two_independent_mean/two_independent_t.py
esek/Calculator/two_independent_mean/two_independent_unequal_var.py
esek/Calculator/two_independent_mean/two_independent_z.py
esek/Calculator/two_paired_mean/__init__.py
esek/Calculator/two_paired_mean/two_paired_aparametric.py
esek/Calculator/two_paired_mean/two_paired_common_lang.py
esek/Calculator/two_paired_mean/two_paired_robust.py
esek/Calculator/two_paired_mean/two_paired_t.py
esek/Calculator/two_paired_mean/two_paired_z.py
esek/utils/__init__.py
esek/utils/effect_sizes.py
esek/utils/interfaces.py
esek/utils/results.py
esek/utils/texts.py
esek/utils/utils.py
esek-0.1.28.dist-info/licenses/LICENSE
esek-0.1.28.dist-info/METADATA
esek-0.1.28.dist-info/WHEEL
esek-0.1.28.dist-info/top_level.txt
esek-0.1.28.dist-info/RECORD
