Metadata-Version: 2.4
Name: esek
Version: 0.1.28
Summary: Effect size estimation and statistics library
Home-page: https://github.com/nadavWeisler/esek
Author: ESEK
Author-email: Nadav Weisler <weisler.nadav@gmail.com>
License: MIT
Requires-Python: >=3.10
License-File: LICENSE
Requires-Dist: numpy>=2.0.2
Requires-Dist: scipy>=1.13.1
Provides-Extra: dev
Requires-Dist: pytest>=7.0; extra == "dev"
Requires-Dist: pytest-cov; extra == "dev"
Dynamic: license-file
